cerebroflow/__init__.py
cerebroflow/gui.py
cerebroflow/kymo.py
cerebroflow-0.0.4.dist-info/METADATA
cerebroflow-0.0.4.dist-info/WHEEL
cerebroflow-0.0.4.dist-info/top_level.txt
cerebroflow-0.0.4.dist-info/RECORD
