Metadata-Version: 2.1
Name: cerebroflow
Version: 0.0.4
Summary: Cerebroflow python package
Author: Quillan Favey
Author-email: <quillan.favey@uzh.ch>
Keywords: python,csf,kymograph
Classifier: Development Status :: 3 - Alpha
Classifier: Intended Audience :: Education
Classifier: Programming Language :: Python :: 3
Classifier: Operating System :: Microsoft :: Windows
Requires-Dist: matplotlib
Requires-Dist: PySimpleGUI
Requires-Dist: opencv-python
Requires-Dist: scipy
Requires-Dist: scikit-image
Requires-Dist: TiffCapture
Requires-Dist: pandas
